cashstatistic/__init__.py
cashstatistic/cashstatistic.py
cashstatistic-0.1.3.dist-info/LICENSE
cashstatistic-0.1.3.dist-info/METADATA
cashstatistic-0.1.3.dist-info/WHEEL
cashstatistic-0.1.3.dist-info/top_level.txt
cashstatistic-0.1.3.dist-info/RECORD
