Metadata-Version: 2.1
Name: cashstatistic
Version: 0.1.3
Summary: Utility functions related to the Cash statistic
Home-page: https://github.com/abmantz/cstat
Author: Adam Mantz
Author-email: amantz@stanford.edu
License: MIT
Platform: UNKNOWN
Classifier: Development Status :: 4 - Beta
Classifier: Intended Audience :: Science/Research
Classifier: License :: OSI Approved :: MIT License
Classifier: Programming Language :: Python :: 2
Classifier: Programming Language :: Python :: 2.7
Classifier: Programming Language :: Python :: 3
Requires-Dist: numpy
